smartcar/__init__.py
smartcar/auth_client.py
smartcar/config.py
smartcar/exception.py
smartcar/helpers.py
smartcar/smartcar.py
smartcar/types.py
smartcar/vehicle.py
smartcar-6.18.3.dist-info/licenses/LICENSE.md
smartcar-6.18.3.dist-info/METADATA
smartcar-6.18.3.dist-info/WHEEL
smartcar-6.18.3.dist-info/top_level.txt
smartcar-6.18.3.dist-info/RECORD
