Metadata-Version: 2.4
Name: smartcar
Version: 6.18.3
Summary: Smartcar Python SDK
Home-page: https://github.com/smartcar/python-sdk
Author: Smartcar
Author-email: hello@smartcar.com
License: MIT
License-File: LICENSE.md
Requires-Dist: python-dateutil
Requires-Dist: requests
Provides-Extra: dev
Requires-Dist: black; extra == "dev"
Requires-Dist: ipdb; extra == "dev"
Requires-Dist: mock; extra == "dev"
Requires-Dist: responses; extra == "dev"
Requires-Dist: pytest; extra == "dev"
Requires-Dist: pytest-cov; extra == "dev"
Requires-Dist: selenium; extra == "dev"
Requires-Dist: retrying; extra == "dev"
Requires-Dist: wheel; extra == "dev"
Dynamic: author
Dynamic: author-email
Dynamic: description
Dynamic: description-content-type
Dynamic: home-page
Dynamic: license
Dynamic: license-file
Dynamic: provides-extra
Dynamic: requires-dist
Dynamic: summary
